dma_controller.v
// =============================================================================
// DMA Controller for 4x4 Systolic Array Matrix Multiplier
// =============================================================================
// Description:
//   1. CPU asserts `start` with base addresses for matrix A and B
//   2. DMA fetches all 16 elements of A (256b burst), then all 16 of B
//   3. DMA streams skewed (zero-padded) rows/cols to systolic array
//      - Each cycle: 4 row entries (A) and 4 col entries (B), each 16-bit
//      - Skewing: row i of A delayed by i cycles, col j of B delayed by j cycles
//   4. After 2N-1+N = 11 cycles of SA operation, DMA asserts `done`
//
// Interface assumptions:
//   - Memory bus: 256-bit wide (fetches entire 4x4 matrix in one transaction)
//   - Systolic array: expects sa_en, sa_row_data[63:0], sa_col_data[63:0]
//     sa_row_data = {row3[15:0], row2[15:0], row1[15:0], row0[15:0]}
//     sa_col_data = {col3[15:0], col2[15:0], col1[15:0], col0[15:0]}
// =============================================================================

module dma_controller #(
    parameter DATA_WIDTH  = 16,   // bits per matrix element
    parameter MAT_SIZE    = 4,    // NxN matrix
    parameter ADDR_WIDTH  = 32,   // memory address width
    parameter MEM_WIDTH   = 256   // memory bus width (full matrix at once)
)(
    input  wire                  clk,
    input  wire                  rst_n,

    // --- CPU Interface ---
    input  wire                  cpu_start,       // pulse to begin
    input  wire [ADDR_WIDTH-1:0] cpu_addr_a,      // base address of matrix A
    input  wire [ADDR_WIDTH-1:0] cpu_addr_b,      // base address of matrix B
    output reg                   dma_done,        // pulse when SA is done

    // --- Memory Interface (burst: 256-bit read in one transaction) ---
    output reg                   mem_req,         // request a memory read
    output reg  [ADDR_WIDTH-1:0] mem_addr,        // address to read
    input  wire                  mem_ack,         // memory data is valid
    input  wire [MEM_WIDTH-1:0]  mem_data,        // 256-bit data back

    // --- Systolic Array Interface ---
    output reg                   sa_en,           // enable / data-valid to SA
    output reg  [63:0]           sa_row_data,     // 4 x 16-bit row entries (A)
    output reg  [63:0]           sa_col_data      // 4 x 16-bit col entries (B)
);

    // -------------------------------------------------------------------------
    // Local parameters
    // -------------------------------------------------------------------------
    localparam N          = MAT_SIZE;             // 4
    localparam TOTAL_ELEM = N * N;                // 16
    // Systolic array needs 2*N-1 + N - 1 = 2N + N - 2 = 10 cycles (0..10)
    // Last diagonal starts at cycle 2*(N-1) = 6, last PE finishes N cycles later
    // Total feed cycles = 2*N - 1 = 7, drain = N-1 extra = 3 → 10 total SA cycles
    localparam SA_CYCLES  = 2*N - 1 + N - 1;     // = 10  (cycles 0..9 inclusive)

    // FSM states
    localparam [2:0]
        S_IDLE      = 3'd0,
        S_FETCH_A   = 3'd1,
        S_FETCH_B   = 3'd2,
        S_STREAM    = 3'd3,
        S_DONE      = 3'd4;

    // -------------------------------------------------------------------------
    // Internal registers
    // -------------------------------------------------------------------------
    reg [2:0]  state, next_state;

    // Matrix storage: mat_a[i][j] = A[i][j], mat_b[i][j] = B[i][j]
    // Stored row-major: mat_a[row*N + col]
    reg [DATA_WIDTH-1:0] mat_a [0:TOTAL_ELEM-1];
    reg [DATA_WIDTH-1:0] mat_b [0:TOTAL_ELEM-1];

    reg [ADDR_WIDTH-1:0] addr_a_r, addr_b_r;

    // Stream counter: which SA cycle are we on (0 to SA_CYCLES)
    reg [$clog2(SA_CYCLES+2)-1:0] sa_cycle;

    integer i; // for unpack loop

    // -------------------------------------------------------------------------
    // FSM — sequential
    // -------------------------------------------------------------------------
    always @(posedge clk or negedge rst_n) begin
        if (!rst_n)
            state <= S_IDLE;
        else
            state <= next_state;
    end

    // -------------------------------------------------------------------------
    // FSM — next-state logic
    // -------------------------------------------------------------------------
    always @(*) begin
        next_state = state;
        case (state)
            S_IDLE:    if (cpu_start)          next_state = S_FETCH_A;
            S_FETCH_A: if (mem_ack)            next_state = S_FETCH_B;
            S_FETCH_B: if (mem_ack)            next_state = S_STREAM;
            S_STREAM:  if (sa_cycle == SA_CYCLES) next_state = S_DONE;
            S_DONE:                            next_state = S_IDLE;
        endcase
    end

    // -------------------------------------------------------------------------
    // Address latch
    // -------------------------------------------------------------------------
    always @(posedge clk or negedge rst_n) begin
        if (!rst_n) begin
            addr_a_r <= 0;
            addr_b_r <= 0;
        end else if (cpu_start) begin
            addr_a_r <= cpu_addr_a;
            addr_b_r <= cpu_addr_b;
        end
    end

    // -------------------------------------------------------------------------
    // Memory request
    // -------------------------------------------------------------------------
    always @(posedge clk or negedge rst_n) begin
        if (!rst_n) begin
            mem_req  <= 1'b0;
            mem_addr <= 0;
        end else begin
            mem_req  <= 1'b0;  // default de-assert
            case (state)
                S_IDLE: begin
                    if (cpu_start) begin
                        mem_req  <= 1'b1;
                        mem_addr <= cpu_addr_a;
                    end
                end
                S_FETCH_A: begin
                    if (!mem_ack) begin
                        mem_req  <= 1'b1;
                        mem_addr <= addr_a_r;
                    end else begin
                        // immediately request B
                        mem_req  <= 1'b1;
                        mem_addr <= addr_b_r;
                    end
                end
                S_FETCH_B: begin
                    if (!mem_ack) begin
                        mem_req  <= 1'b1;
                        mem_addr <= addr_b_r;
                    end
                end
                default: ;
            endcase
        end
    end

    // -------------------------------------------------------------------------
    // Matrix unpack from 256-bit burst
    // mem_data layout: element[0] in bits [15:0], element[15] in bits [255:240]
    // Row-major: index = row*4 + col
    // -------------------------------------------------------------------------
    always @(posedge clk or negedge rst_n) begin
        if (!rst_n) begin
            for (i = 0; i < TOTAL_ELEM; i = i + 1) begin
                mat_a[i] <= 0;
                mat_b[i] <= 0;
            end
        end else begin
            if (state == S_FETCH_A && mem_ack) begin
                for (i = 0; i < TOTAL_ELEM; i = i + 1)
                    mat_a[i] <= mem_data[i*DATA_WIDTH +: DATA_WIDTH];
            end
            if (state == S_FETCH_B && mem_ack) begin
                for (i = 0; i < TOTAL_ELEM; i = i + 1)
                    mat_b[i] <= mem_data[i*DATA_WIDTH +: DATA_WIDTH];
            end
        end
    end

    // -------------------------------------------------------------------------
    // SA cycle counter
    // -------------------------------------------------------------------------
    always @(posedge clk or negedge rst_n) begin
        if (!rst_n)
            sa_cycle <= 0;
        else if (state == S_STREAM)
            sa_cycle <= sa_cycle + 1;
        else
            sa_cycle <= 0;
    end

    // -------------------------------------------------------------------------
    // Systolic array data steering
    //
    // Skewing rule (same as the systolic array diagram):
    //   A: row i of matrix A enters at SA cycle i, i+1, i+2, i+3
    //      i.e. A[i][k] is valid when sa_cycle == i + k
    //      → for a given sa_cycle t, row i gets A[i][t-i] if 0 <= t-i < N
    //
    //   B: col j of matrix B enters at SA cycle j, j+1, j+2, j+3
    //      i.e. B[k][j] is valid when sa_cycle == j + k
    //      → for a given sa_cycle t, col j gets B[t-j][j] if 0 <= t-j < N
    //
    // sa_row_data[row] = (t-row in [0,N-1]) ? A[row][t-row] : 0
    // sa_col_data[col] = (t-col in [0,N-1]) ? B[t-col][col] : 0
    // -------------------------------------------------------------------------

    // Helper function: get A[row][k], or 0 if k out of range
    // Verilog doesn't allow functions returning 'wire' arrays easily,
    // so we use combinational always with internal variables.

    reg [DATA_WIDTH-1:0] row_val [0:N-1]; // what goes to SA row port each cycle
    reg [DATA_WIDTH-1:0] col_val [0:N-1]; // what goes to SA col port each cycle

    integer row, col, k_r, k_c;

    always @(*) begin
        for (row = 0; row < N; row = row + 1) begin
            k_r = $signed(sa_cycle) - row;
            if (k_r >= 0 && k_r < N)
                row_val[row] = mat_a[row*N + k_r];
            else
                row_val[row] = {DATA_WIDTH{1'b0}};
        end

        for (col = 0; col < N; col = col + 1) begin
            k_c = $signed(sa_cycle) - col;
            if (k_c >= 0 && k_c < N)
                col_val[col] = mat_b[k_c*N + col];
            else
                col_val[col] = {DATA_WIDTH{1'b0}};
        end
    end

    // -------------------------------------------------------------------------
    // SA output registers
    // -------------------------------------------------------------------------
    always @(posedge clk or negedge rst_n) begin
        if (!rst_n) begin
            sa_en       <= 1'b0;
            sa_row_data <= 64'b0;
            sa_col_data <= 64'b0;
        end else begin
            sa_en <= (state == S_STREAM);
            if (state == S_STREAM) begin
                // Pack: sa_row_data[16*(row+1)-1 : 16*row] = row_val[row]
                sa_row_data <= {row_val[3], row_val[2], row_val[1], row_val[0]};
                sa_col_data <= {col_val[3], col_val[2], col_val[1], col_val[0]};
            end else begin
                sa_row_data <= 64'b0;
                sa_col_data <= 64'b0;
            end
        end
    end

    // -------------------------------------------------------------------------
    // Done signal (one-cycle pulse)
    // -------------------------------------------------------------------------
    always @(posedge clk or negedge rst_n) begin
        if (!rst_n)
            dma_done <= 1'b0;
        else
            dma_done <= (state == S_DONE);
    end

endmodule

DMA_controller/tb_dma_controller.v
// =============================================================================
// Testbench for dma_controller
// Tests: A = [[1,2,0,0],[3,4,0,0],[0,0,1,0],[0,0,0,2]]
//        B = [[5,6,0,0],[7,8,0,0],[0,0,3,0],[0,0,0,4]]
//        Expected C[0][0] = 1*5+2*7 = 19, C[0][1] = 1*6+2*8 = 22, etc.
// =============================================================================

`timescale 1ns/1ps

module tb_dma_controller;

    parameter DATA_WIDTH = 16;
    parameter MAT_SIZE   = 4;
    parameter ADDR_WIDTH = 32;
    parameter MEM_WIDTH  = 256;
    parameter N          = MAT_SIZE;

    // DUT signals
    reg                   clk, rst_n;
    reg                   cpu_start;
    reg  [ADDR_WIDTH-1:0] cpu_addr_a, cpu_addr_b;
    wire                  dma_done;
    wire                  mem_req;
    wire [ADDR_WIDTH-1:0] mem_addr;
    reg                   mem_ack;
    reg  [MEM_WIDTH-1:0]  mem_data;
    wire                  sa_en;
    wire [63:0]           sa_row_data, sa_col_data;

    // DUT
    dma_controller #(
        .DATA_WIDTH(DATA_WIDTH),
        .MAT_SIZE  (MAT_SIZE),
        .ADDR_WIDTH(ADDR_WIDTH),
        .MEM_WIDTH (MEM_WIDTH)
    ) dut (
        .clk         (clk),
        .rst_n       (rst_n),
        .cpu_start   (cpu_start),
        .cpu_addr_a  (cpu_addr_a),
        .cpu_addr_b  (cpu_addr_b),
        .dma_done    (dma_done),
        .mem_req     (mem_req),
        .mem_addr    (mem_addr),
        .mem_ack     (mem_ack),
        .mem_data    (mem_data),
        .sa_en       (sa_en),
        .sa_row_data (sa_row_data),
        .sa_col_data (sa_col_data)
    );

    // Clock: 10ns period
    always #5 clk = ~clk;

    // Matrix A = [[1,2,0,0],[3,4,0,0],[0,0,1,0],[0,0,0,2]] row-major
    // Element order in 256-bit word: [15:0]=A[0][0]=1, [31:16]=A[0][1]=2, ...
    reg [MEM_WIDTH-1:0] mem_a, mem_b;
    integer i;

    task build_matrix_word;
        input [15:0] e0,e1,e2,e3,e4,e5,e6,e7,e8,e9,e10,e11,e12,e13,e14,e15;
        output [MEM_WIDTH-1:0] word;
        begin
            word = {e15,e14,e13,e12, e11,e10,e9,e8, e7,e6,e5,e4, e3,e2,e1,e0};
        end
    endtask

    initial begin
        // Build A word: row-major [1,2,0,0, 3,4,0,0, 0,0,1,0, 0,0,0,2]
        build_matrix_word(16'd1,16'd2,16'd0,16'd0,
                          16'd3,16'd4,16'd0,16'd0,
                          16'd0,16'd0,16'd1,16'd0,
                          16'd0,16'd0,16'd0,16'd2,
                          mem_a);

        // Build B word: [5,6,0,0, 7,8,0,0, 0,0,3,0, 0,0,0,4]
        build_matrix_word(16'd5,16'd6,16'd0,16'd0,
                          16'd7,16'd8,16'd0,16'd0,
                          16'd0,16'd0,16'd3,16'd0,
                          16'd0,16'd0,16'd0,16'd4,
                          mem_b);
    end

    // Simple memory model: 1-cycle latency
    reg pending_ack;
    reg [MEM_WIDTH-1:0] pending_data;

    always @(posedge clk or negedge rst_n) begin
        if (!rst_n) begin
            mem_ack      <= 0;
            mem_data     <= 0;
            pending_ack  <= 0;
        end else begin
            mem_ack <= 0;
            if (mem_req && !mem_ack) begin
                // Return A or B based on address
                if (mem_addr == 32'hAAAA_0000)
                    mem_data <= mem_a;
                else
                    mem_data <= mem_b;
                mem_ack <= 1;
            end
        end
    end

    // Waveform dump
    initial begin
        $dumpfile("tb_dma.vcd");
        $dumpvars(0, tb_dma_controller);
    end

    // Monitor SA inputs
    integer cycle_cnt;
    always @(posedge clk) begin
        if (sa_en) begin
            $display("SA cycle %0d | row_data=%016h  col_data=%016h",
                     cycle_cnt,
                     sa_row_data, sa_col_data);
            $display("         row: [%0d,%0d,%0d,%0d]  col: [%0d,%0d,%0d,%0d]",
                     sa_row_data[15:0],  sa_row_data[31:16],
                     sa_row_data[47:32], sa_row_data[63:48],
                     sa_col_data[15:0],  sa_col_data[31:16],
                     sa_col_data[47:32], sa_col_data[63:48]);
            cycle_cnt = cycle_cnt + 1;
        end
    end

    // Main test
    initial begin
        clk         = 0;
        rst_n       = 0;
        cpu_start   = 0;
        cpu_addr_a  = 32'hAAAA_0000;
        cpu_addr_b  = 32'hBBBB_0000;
        mem_ack     = 0;
        mem_data    = 0;
        cycle_cnt   = 0;

        @(posedge clk); #1;
        rst_n = 1;

        @(posedge clk); #1;
        $display("\n=== DMA Controller Test ===");
        $display("Matrix A: [[1,2,0,0],[3,4,0,0],[0,0,1,0],[0,0,0,2]]");
        $display("Matrix B: [[5,6,0,0],[7,8,0,0],[0,0,3,0],[0,0,0,4]]");
        $display("Expected C[0][0]=19, C[0][1]=22, C[1][0]=43, C[1][1]=50\n");

        // Start DMA
        cpu_start = 1;
        @(posedge clk); #1;
        cpu_start = 0;

        // Wait for done
        @(posedge dma_done);
        $display("\n=== DMA done signal received ===\n");

        #20;
        $finish;
    end

endmodule

DMA_controller/tb_dma.vcd
$date
	Fri Mar 20 17:13:21 2026
$end
$version
	Icarus Verilog
$end
$timescale
	1ps
$end
$scope module tb_dma_controller $end
$var wire 64 ! sa_row_data [63:0] $end
$var wire 1 " sa_en $end
$var wire 64 # sa_col_data [63:0] $end
$var wire 1 $ mem_req $end
$var wire 32 % mem_addr [31:0] $end
$var wire 1 & dma_done $end
$var parameter 32 ' ADDR_WIDTH $end
$var parameter 32 ( DATA_WIDTH $end
$var parameter 32 ) MAT_SIZE $end
$var parameter 32 * MEM_WIDTH $end
$var parameter 32 + N $end
$var reg 1 , clk $end
$var reg 32 - cpu_addr_a [31:0] $end
$var reg 32 . cpu_addr_b [31:0] $end
$var reg 1 / cpu_start $end
$var reg 256 0 mem_a [255:0] $end
$var reg 1 1 mem_ack $end
$var reg 256 2 mem_b [255:0] $end
$var reg 256 3 mem_data [255:0] $end
$var reg 1 4 pending_ack $end
$var reg 1 5 rst_n $end
$var integer 32 6 cycle_cnt [31:0] $end
$scope module dut $end
$var wire 1 , clk $end
$var wire 32 7 cpu_addr_a [31:0] $end
$var wire 32 8 cpu_addr_b [31:0] $end
$var wire 1 / cpu_start $end
$var wire 1 1 mem_ack $end
$var wire 256 9 mem_data [255:0] $end
$var wire 1 5 rst_n $end
$var parameter 32 : ADDR_WIDTH $end
$var parameter 32 ; DATA_WIDTH $end
$var parameter 32 < MAT_SIZE $end
$var parameter 32 = MEM_WIDTH $end
$var parameter 32 > N $end
$var parameter 67 ? SA_CYCLES $end
$var parameter 3 @ S_DONE $end
$var parameter 3 A S_FETCH_A $end
$var parameter 3 B S_FETCH_B $end
$var parameter 3 C S_IDLE $end
$var parameter 3 D S_STREAM $end
$var parameter 64 E TOTAL_ELEM $end
$var reg 32 F addr_a_r [31:0] $end
$var reg 32 G addr_b_r [31:0] $end
$var reg 1 & dma_done $end
$var reg 32 H mem_addr [31:0] $end
$var reg 1 $ mem_req $end
$var reg 3 I next_state [2:0] $end
$var reg 64 J sa_col_data [63:0] $end
$var reg 4 K sa_cycle [3:0] $end
$var reg 1 " sa_en $end
$var reg 64 L sa_row_data [63:0] $end
$var reg 3 M state [2:0] $end
$var integer 32 N col [31:0] $end
$var integer 32 O i [31:0] $end
$var integer 32 P k_c [31:0] $end
$var integer 32 Q k_r [31:0] $end
$var integer 32 R row [31:0] $end
$upscope $end
$scope task build_matrix_word $end
$var reg 16 S e0 [15:0] $end
$var reg 16 T e1 [15:0] $end
$var reg 16 U e10 [15:0] $end
$var reg 16 V e11 [15:0] $end
$var reg 16 W e12 [15:0] $end
$var reg 16 X e13 [15:0] $end
$var reg 16 Y e14 [15:0] $end
$var reg 16 Z e15 [15:0] $end
$var reg 16 [ e2 [15:0] $end
$var reg 16 \ e3 [15:0] $end
$var reg 16 ] e4 [15:0] $end
$var reg 16 ^ e5 [15:0] $end
$var reg 16 _ e6 [15:0] $end
$var reg 16 ` e7 [15:0] $end
$var reg 16 a e8 [15:0] $end
$var reg 16 b e9 [15:0] $end
$var reg 256 c word [255:0] $end
$upscope $end
$upscope $end
$enddefinitions $end
$comment Show the parameter values. $end
$dumpall
b10000 E
b11 D
b0 C
b10 B
b1 A
b100 @
b1010 ?
b100 >
b100000000 =
b100 <
b10000 ;
b100000 :
b100 +
b100000000 *
b100 )
b10000 (
b100000 '
$end
#0
$dumpvars
b100000000000000000000000000000000000000000000000000000000000000000000000000000000110000000000000000000000000000000000000000000000000000000000000000000000000000100000000000000001110000000000000000000000000000000000000000000001100000000000000101 c
b0 b
b0 a
b0 `
b0 _
b1000 ^
b111 ]
b0 \
b0 [
b100 Z
b0 Y
b0 X
b0 W
b0 V
b11 U
b110 T
b101 S
b100 R
b11111111111111111111111111111101 Q
b11111111111111111111111111111101 P
b10000 O
b100 N
b0 M
b0 L
b0 K
b0 J
b0 I
b0 H
b0 G
b0 F
b0 9
b10111011101110110000000000000000 8
b10101010101010100000000000000000 7
b0 6
05
04
b0 3
b100000000000000000000000000000000000000000000000000000000000000000000000000000000110000000000000000000000000000000000000000000000000000000000000000000000000000100000000000000001110000000000000000000000000000000000000000000001100000000000000101 2
01
b10000000000000000000000000000000000000000000000000000000000000000000000000000000010000000000000000000000000000000000000000000000000000000000000000000000000000010000000000000000110000000000000000000000000000000000000000000000100000000000000001 0
0/
b10111011101110110000000000000000 .
b10101010101010100000000000000000 -
0,
0&
b0 %
0$
b0 #
0"
b0 !
$end
#5000
b10000 O
1,
#6000
15
#10000
0,
#15000
1,
#16000
b1 I
1/
#20000
0,
#25000
b10101010101010100000000000000000 %
b10101010101010100000000000000000 H
1$
b10111011101110110000000000000000 G
b10101010101010100000000000000000 F
b1 M
1,
#26000
0/
#30000
0,
#35000
b10 I
1$
11
b10000000000000000000000000000000000000000000000000000000000000000000000000000000010000000000000000000000000000000000000000000000000000000000000000000000000000010000000000000000110000000000000000000000000000000000000000000000100000000000000001 3
b10000000000000000000000000000000000000000000000000000000000000000000000000000000010000000000000000000000000000000000000000000000000000000000000000000000000000010000000000000000110000000000000000000000000000000000000000000000100000000000000001 9
1,
#40000
0,
#45000
b11111111111111111111111111111101 P
b100 N
b11111111111111111111111111111101 Q
b100 R
01
b10111011101110110000000000000000 %
b10111011101110110000000000000000 H
1$
b10 M
b10000 O
1,
#50000
0,
#55000
b11 I
1$
11
b100000000000000000000000000000000000000000000000000000000000000000000000000000000110000000000000000000000000000000000000000000000000000000000000000000000000000100000000000000001110000000000000000000000000000000000000000000001100000000000000101 3
b100000000000000000000000000000000000000000000000000000000000000000000000000000000110000000000000000000000000000000000000000000000000000000000000000000000000000100000000000000001110000000000000000000000000000000000000000000001100000000000000101 9
1,
#60000
0,
#65000
b11111111111111111111111111111101 P
b100 N
b11111111111111111111111111111101 Q
b100 R
01
0$
b11 M
b10000 O
1,
#70000
0,
#75000
b11111111111111111111111111111110 P
b100 N
b11111111111111111111111111111110 Q
b100 R
b1 K
b101 #
b101 J
b1 !
b1 L
1"
1,
#80000
0,
#85000
b11111111111111111111111111111111 P
b100 N
b11111111111111111111111111111111 Q
b100 R
b1100000000000000111 #
b1100000000000000111 J
b110000000000000010 !
b110000000000000010 L
b10 K
b1 6
1,
#90000
0,
#95000
b0 P
b100 N
b0 Q
b100 R
b11 K
b10000000000000000000 #
b10000000000000000000 J
b1000000000000000000 !
b1000000000000000000 L
b10 6
1,
#100000
0,
#105000
b1 P
b100 N
b1 Q
b100 R
b0 #
b0 J
b0 !
b0 L
b100 K
b11 6
1,
#110000
0,
#115000
b10 P
b100 N
b10 Q
b100 R
b101 K
b1100000000000000000000000000000000 #
b1100000000000000000000000000000000 J
b100000000000000000000000000000000 !
b100000000000000000000000000000000 L
b100 6
1,
#120000
0,
#125000
b11 P
b100 N
b11 Q
b100 R
b0 #
b0 J
b0 !
b0 L
b110 K
b101 6
1,
#130000
0,
#135000
b100 P
b100 N
b100 Q
b100 R
b111 K
b100000000000000000000000000000000000000000000000000 #
b100000000000000000000000000000000000000000000000000 J
b10000000000000000000000000000000000000000000000000 !
b10000000000000000000000000000000000000000000000000 L
b110 6
1,
#140000
0,
#145000
b11111111111111111111111111110101 P
b100 N
b11111111111111111111111111110101 Q
b100 R
b0 #
b0 J
b0 !
b0 L
b1000 K
b111 6
1,
#150000
0,
#155000
b11111111111111111111111111110110 P
b100 N
b11111111111111111111111111110110 Q
b100 R
b1001 K
b1000 6
1,
#160000
0,
#165000
b11111111111111111111111111110111 P
b100 N
b11111111111111111111111111110111 Q
b100 R
b100 I
b1010 K
b1001 6
1,
#170000
0,
#175000
b11111111111111111111111111111000 P
b100 N
b11111111111111111111111111111000 Q
b100 R
b0 I
b100 M
b1011 K
b1010 6
1,
#180000
0,
#185000
b11111111111111111111111111111101 P
b100 N
b11111111111111111111111111111101 Q
b100 R
1&
0"
b0 K
b0 M
b1011 6
1,
#190000
0,
#195000
0&
1,
